polygon_sdk/__init__.py
polygon_sdk/aggregates.py
polygon_sdk/async_polygon_sdk.py
polygon_sdk/company_info.py
polygon_sdk/conditions.py
polygon_sdk/daily_open_close.py
polygon_sdk/dictionaries.py
polygon_sdk/ema.py
polygon_sdk/embeddings.py
polygon_sdk/extra_data.py
polygon_sdk/financials.py
polygon_sdk/helpers.py
polygon_sdk/indices_snapshot.py
polygon_sdk/logo.py
polygon_sdk/macd.py
polygon_sdk/models.py
polygon_sdk/pivot_points.py
polygon_sdk/quote.py
polygon_sdk/snapshot.py
polygon_sdk/tickernews.py
polygon_sdk/mapping/mapping_dicts.py
polygon_sdk/options_market/async_options_sdk.py
polygon_sdk/options_market/daily_oc.py
polygon_sdk/options_market/get_all_options.py
polygon_sdk/options_market/option_aggs.py
polygon_sdk/options_market/option_snapshot.py
polygon_sdk/options_market/option_trades.py
polygon_sdk/test_events/test_stock.py
polygon_sdk-1.1.0.dist-info/METADATA
polygon_sdk-1.1.0.dist-info/WHEEL
polygon_sdk-1.1.0.dist-info/top_level.txt
polygon_sdk-1.1.0.dist-info/RECORD
