Metadata-Version: 2.1
Name: polygon-sdk
Version: 1.1.0
Requires-Python: >=3.6
Requires-Dist: aiofiles (==23.1.0)
Requires-Dist: aiohttp (==3.8.4)
Requires-Dist: aiosignal (==1.3.1)
Requires-Dist: anaconda-client (==1.11.2)
Requires-Dist: anaconda-navigator (==2.4.0)
Requires-Dist: anyio (==3.6.2)
Requires-Dist: async-generator (==1.10)
Requires-Dist: async-timeout (==4.0.2)
Requires-Dist: attrs (==23.1.0)
Requires-Dist: backports.functools-lru-cache
Requires-Dist: backports.tempfile
Requires-Dist: backports.weakref (==1.0.post1)
Requires-Dist: beautifulsoup4
Requires-Dist: boltons
Requires-Dist: brotlipy (==0.7.0)
Requires-Dist: cachetools (==5.2.0)
Requires-Dist: certifi
Requires-Dist: cffi
Requires-Dist: chardet
Requires-Dist: charset-normalizer (==2.1.1)
Requires-Dist: click (==8.1.3)
Requires-Dist: clyent (==1.2.1)
Requires-Dist: colorama
Requires-Dist: contourpy (==1.0.7)
Requires-Dist: cryptography
Requires-Dist: cycler (==0.11.0)
Requires-Dist: defusedxml
Requires-Dist: discord
Requires-Dist: discord-webhook (==1.1.0)
Requires-Dist: discord.py (==2.2.3)
Requires-Dist: disnake (==2.8.1)
Requires-Dist: exceptiongroup (==1.1.1)
Requires-Dist: fastjsonschema
Requires-Dist: filelock
Requires-Dist: fonttools (==4.39.3)
Requires-Dist: frozenlist (==1.3.3)
Requires-Dist: fsspec (==2023.5.0)
Requires-Dist: future
Requires-Dist: glob2
Requires-Dist: grpcio (==1.51.1)
Requires-Dist: grpcio-tools (==1.51.1)
Requires-Dist: h11 (==0.14.0)
Requires-Dist: httpcore (==0.17.0)
Requires-Dist: httpx (==0.24.0)
Requires-Dist: huggingface-hub (==0.14.1)
Requires-Dist: idna
Requires-Dist: imgurpython (==1.1.7)
Requires-Dist: Jinja2
Requires-Dist: jmespath (==0.10.0)
Requires-Dist: joblib (==1.2.0)
Requires-Dist: jsonpatch
Requires-Dist: jsonpointer (==2.1)
Requires-Dist: jsonschema
Requires-Dist: jupyter-core
Requires-Dist: kiwisolver (==1.4.4)
Requires-Dist: libarchive-c
Requires-Dist: MarkupSafe
Requires-Dist: matplotlib (==3.7.1)
Requires-Dist: menuinst
Requires-Dist: mplfinance (==0.12.9b7)
Requires-Dist: mpmath (==1.3.0)
Requires-Dist: multidict (==6.0.4)
Requires-Dist: navigator-updater (==0.3.0)
Requires-Dist: nbformat (==5.4.0)
Requires-Dist: networkx (==3.1)
Requires-Dist: nltk (==3.8)
Requires-Dist: numpy (==1.24.3)
Requires-Dist: openai (==0.27.6)
Requires-Dist: outcome (==1.2.0)
Requires-Dist: packaging
Requires-Dist: paho-mqtt (==1.6.1)
Requires-Dist: pandas (==2.0.1)
Requires-Dist: pathlib
Requires-Dist: pdfminer.six
Requires-Dist: pdfplumber (==0.9.0)
Requires-Dist: Pillow (==9.4.0)
Requires-Dist: pkginfo
Requires-Dist: platformdirs
Requires-Dist: plotly (==5.14.1)
Requires-Dist: pluggy
Requires-Dist: ply (==3.11)
Requires-Dist: polygon (==1.1.0)
Requires-Dist: polygon-api-client (==1.8.5)
Requires-Dist: protobuf (==4.21.12)
Requires-Dist: psutil
Requires-Dist: pycosat
Requires-Dist: pycparser
Requires-Dist: PyJWT
Requires-Dist: pyOpenSSL
Requires-Dist: pyparsing (==3.0.9)
Requires-Dist: PyPDF2 (==3.0.1)
Requires-Dist: PyQt5 (==5.15.7)
Requires-Dist: PyQt5-sip
Requires-Dist: pyrsistent
Requires-Dist: PySocks
Requires-Dist: python-dateutil
Requires-Dist: pytz
Requires-Dist: pywin32
Requires-Dist: PyYAML
Requires-Dist: QtPy
Requires-Dist: regex (==2023.5.5)
Requires-Dist: requests (==2.30.0)
Requires-Dist: requests-mock (==1.10.0)
Requires-Dist: requests-toolbelt
Requires-Dist: ruamel-yaml-conda
Requires-Dist: ruamel.yaml
Requires-Dist: ruamel.yaml.clib
Requires-Dist: scipy (==1.10.1)
Requires-Dist: seaborn (==0.12.2)
Requires-Dist: selenium (==4.9.1)
Requires-Dist: sip
Requires-Dist: six
Requires-Dist: sniffio (==1.3.0)
Requires-Dist: sortedcontainers (==2.4.0)
Requires-Dist: soupsieve
Requires-Dist: sympy (==1.11.1)
Requires-Dist: tabulate (==0.9.0)
Requires-Dist: tenacity (==8.2.2)
Requires-Dist: tokenizers (==0.13.3)
Requires-Dist: toml
Requires-Dist: tomli
Requires-Dist: toolz
Requires-Dist: torch (==2.0.1)
Requires-Dist: torchvision (==0.15.2)
Requires-Dist: tornado
Requires-Dist: tqdm
Requires-Dist: traitlets
Requires-Dist: transformers (==4.28.1)
Requires-Dist: trio (==0.22.0)
Requires-Dist: trio-websocket (==0.10.2)
Requires-Dist: typing-extensions (==4.5.0)
Requires-Dist: tzdata (==2023.3)
Requires-Dist: ujson
Requires-Dist: urllib3
Requires-Dist: Wand (==0.6.11)
Requires-Dist: win-inet-pton
Requires-Dist: wincertstore
Requires-Dist: wsproto (==1.2.0)
Requires-Dist: yarl (==1.9.2)
Requires-Dist: zstandard (==0.19.0)
